odoo/addons/web_button_no_save/README.rst
odoo/addons/web_button_no_save/__init__.py
odoo/addons/web_button_no_save/__manifest__.py
odoo/addons/web_button_no_save/i18n/web_button_no_save.pot
odoo/addons/web_button_no_save/readme/CONFIGURE.rst
odoo/addons/web_button_no_save/readme/CONTRIBUTORS.rst
odoo/addons/web_button_no_save/readme/DESCRIPTION.rst
odoo/addons/web_button_no_save/readme/ROADMAP.rst
odoo/addons/web_button_no_save/static/description/icon.png
odoo/addons/web_button_no_save/static/description/index.html
odoo/addons/web_button_no_save/static/src/js/web_button_no_save.js
odoo/addons/web_button_no_save/templates/assets.xml
odoo12_addon_web_button_no_save-12.0.1.0.0.99.dev4.dist-info/METADATA
odoo12_addon_web_button_no_save-12.0.1.0.0.99.dev4.dist-info/WHEEL
odoo12_addon_web_button_no_save-12.0.1.0.0.99.dev4.dist-info/top_level.txt
odoo12_addon_web_button_no_save-12.0.1.0.0.99.dev4.dist-info/RECORD
